LeagueLibrary/__init__.py
LeagueLibrary/host/__init__.py
LeagueLibrary/host/host.py
LeagueLibrary/summoner/__init__.py
LeagueLibrary/summoner/summoner.py
LeagueLibrary-2021.8.15.6.dist-info/LICENSE
LeagueLibrary-2021.8.15.6.dist-info/METADATA
LeagueLibrary-2021.8.15.6.dist-info/WHEEL
LeagueLibrary-2021.8.15.6.dist-info/top_level.txt
LeagueLibrary-2021.8.15.6.dist-info/RECORD
