Metadata-Version: 2.1
Name: LeagueLibrary
Version: 2021.8.15.6
Summary: LeagueLibrary is a library for Python3 based on the origial Riot Games API.
Home-page: https://github.com/Groot-cmd/LeagueLibrary
Author: Gabriel Veras
Author-email: developergabrielveras@gmail.com
License: UNKNOWN
Platform: UNKNOWN
Classifier: Programming Language :: Python :: 3
Classifier: License :: OSI Approved :: MIT License
Classifier: Operating System :: OS Independent
Requires-Python: >=3.9
License-File: LICENSE
Requires-Dist: requests (==2.26.0)
